twjxi/__init__.py
twjxi/tmath.py
twjxi-0.0.1.dist-info/LICENSE
twjxi-0.0.1.dist-info/METADATA
twjxi-0.0.1.dist-info/WHEEL
twjxi-0.0.1.dist-info/top_level.txt
twjxi-0.0.1.dist-info/RECORD
