Metadata-Version: 2.1
Name: twjxi
Version: 0.0.1
Summary: A math package
Home-page: https://github.com/TWJxi/gittest1
Author: twj
Author-email: twjxi@qq.com
License: UNKNOWN
Platform: UNKNOWN
License-File: LICENSE
